asyncddgs/__init__.py
asyncddgs/async_ddgs.py
asyncddgs/exceptions.py
asyncddgs/utils.py
asyncddgs-0.1.0a1.dist-info/licenses/LICENSE
asyncddgs-0.1.0a1.dist-info/METADATA
asyncddgs-0.1.0a1.dist-info/WHEEL
asyncddgs-0.1.0a1.dist-info/top_level.txt
asyncddgs-0.1.0a1.dist-info/RECORD
