Metadata-Version: 2.4
Name: AsyncDDGS
Version: 0.1.0a1
Summary: Asynchronous DuckDuckGo Search API: A FastAPI service for async access to DuckDuckGo’s text, image, video, and news searches. Uses a custom aDDGS class with aiohttp and asyncio for concurrent queries. Supports advanced syntax and proxies.
Author-email: Rah-Rah-Mitra <115509410+Rah-Rah-Mitra@users.noreply.github.com>
Requires-Python: >=3.9
License-File: LICENSE
Requires-Dist: aiohttp
Requires-Dist: lxml
Requires-Dist: fastapi
Requires-Dist: uvicorn
Dynamic: license-file
